setup_server.py
server/__init__.py
server/decos.py
server/descriptors.py
server/errors.py
server/metaclasses.py
server/server.py
server/config/__init__.py
server/data/__init__.py
server/data/variables.py
server/log_configs/__init__.py
server/log_configs/base_logger.py
server/log_configs/client_log_config.py
server/log_configs/server_log_config.py
server/logs/__init__.py
server/server/__init__.py
server/server/add_user.py
server/server/config_window.py
server/server/core.py
server/server/main_window.py
server/server/remove_user.py
server/server/server_database.py
server/server/stat_window.py
server/unit_tests/__init__.py
server/unit_tests/test_client.py
server/unit_tests/test_server.py
server_project_1.egg-info/PKG-INFO
server_project_1.egg-info/SOURCES.txt
server_project_1.egg-info/dependency_links.txt
server_project_1.egg-info/requires.txt
server_project_1.egg-info/top_level.txt