Metadata-Version: 2.1
Name: server-project-1
Version: 0.0.3
Summary: mess_server_proj_1
Home-page: UNKNOWN
Author: FidelSol
Author-email: fsoloviov2020@mail.ru
License: UNKNOWN
Platform: UNKNOWN
